pathvar/__init__.py
pathvar/project.py
pathvar-1.0.1.dist-info/LICENSE.txt
pathvar-1.0.1.dist-info/METADATA
pathvar-1.0.1.dist-info/WHEEL
pathvar-1.0.1.dist-info/entry_points.txt
pathvar-1.0.1.dist-info/top_level.txt
pathvar-1.0.1.dist-info/RECORD
