Metadata-Version: 2.1
Name: pathvar
Version: 1.0.1
Summary: Interacting with PATH variable from Linux BASH command line.
Author-email: Hussine Mahmoud Kandil <hussein.mahmoud.s7s@gmail.com>
Project-URL: Repository, https://github.com/hussein-m-kandil/pathvar/
Keywords: path,command line,linux,terminal,environment variable,system,os
Classifier: Programming Language :: Python
Requires-Python: >=3.10
License-File: LICENSE.txt
